retry_reloaded/__init__.py
retry_reloaded/_exceptions.py
retry_reloaded/_logging.py
retry_reloaded/_validate.py
retry_reloaded/backoff.py
retry_reloaded/callback.py
retry_reloaded/retry.py
retry_reloaded-0.0.8.dist-info/LICENSE
retry_reloaded-0.0.8.dist-info/METADATA
retry_reloaded-0.0.8.dist-info/WHEEL
retry_reloaded-0.0.8.dist-info/top_level.txt
retry_reloaded-0.0.8.dist-info/RECORD
