Metadata-Version: 2.1
Name: retry-reloaded
Version: 0.0.8
Summary: A simple Python library for retrying functions         with various backoff and callback strategies.
Home-page: https://github.com/chrisK824/retry
Author: Chris Karvouniaris
Author-email: christos.karvouniaris247@gmail.com
Classifier: Programming Language :: Python :: 3
Classifier: License :: OSI Approved :: MIT License
Classifier: Operating System :: OS Independent
Requires-Python: >=3.7
License-File: LICENSE
